pystringutils/__init__.py
pystringutils/cases.py
pystringutils-0.1.1.dist-info/LICENSE
pystringutils-0.1.1.dist-info/METADATA
pystringutils-0.1.1.dist-info/WHEEL
pystringutils-0.1.1.dist-info/top_level.txt
pystringutils-0.1.1.dist-info/RECORD
