Metadata-Version: 2.1
Name: pystringutils
Version: 0.1.1
Summary: A python library for common string operations
Author: Martin Taraz
Author-email: Matteo Voges <matteo.voges@student.hpi.de>
License: MIT License
Requires-Python: >=3.9
License-File: LICENSE
Requires-Dist: pytest ~=8.2.2
Requires-Dist: coverage ~=7.5.3
